minds/__init__.py
minds/api.py
minds/connections.py
minds/endpoints.py
minds/exceptions.py
minds/profile.py
minds/utils.py
minds/sections/__init__.py
minds/sections/channel.py
minds/sections/interact.py
minds/sections/newsfeed.py
minds/sections/notifications.py
minds/sections/posting.py
minds-0.1.2.dist-info/METADATA
minds-0.1.2.dist-info/RECORD
minds-0.1.2.dist-info/WHEEL
minds-0.1.2.dist-info/top_level.txt
