Metadata-Version: 2.1
Name: minds
Version: 0.1.2
Summary: unofficial api for minds.com
Home-page: https://gitlab.com/granitosaurus/minds-api
Author: Bernardas Ališauskas
Author-email: bernardas.alisauskas@pm.me
License: GNU General Public License v3
Keywords: minds
Platform: UNKNOWN
Classifier: Intended Audience :: Developers
Classifier: License :: OSI Approved :: GNU General Public License v3 (GPLv3)
Classifier: Natural Language :: English
Classifier: Programming Language :: Python :: 3.6
Classifier: Programming Language :: Python :: 3.7
Requires-Dist: requests
Requires-Dist: toml
